SkyMapMod/__init__.py
SkyMapMod/airglow.py
SkyMapMod/albedo_of_planets.py
SkyMapMod/band_V_data.py
SkyMapMod/modtran_default_kp_transparency.py
SkyMapMod/planets.py
SkyMapMod/solar_radio_flux.py
SkyMapMod/solar_spectrum.py
SkyMapMod/star_catalogues.py
SkyMapMod/total_background.py
SkyMapMod/transparency.py
SkyMapMod/zodiac.py
SkyMapMod/data/__init__.py
SkyMapMod/data/intensity_kp.npy
SkyMapMod/data/load_data.py
SkyMapMod/data/star_brightness.npy
SkyMapMod/data/star_temperatures.npy
SkyMapMod/data/wavelenght_kp.npy
skymapmod-0.2.7.dist-info/METADATA
skymapmod-0.2.7.dist-info/WHEEL
skymapmod-0.2.7.dist-info/licenses/LICENSE
skymapmod-0.2.7.dist-info/RECORD
