Metadata-Version: 2.4
Name: SkyMapMod
Version: 0.2.7
Summary: A numerical model of the night sky brightness in the optical range
Project-URL: Homepage, https://istina.msu.ru/profile/aminevann/
Author-email: Anna Amineva <amineva.2219@physics.msu.ru>
License-File: LICENSE
Classifier: License :: OSI Approved :: MIT License
Classifier: Operating System :: OS Independent
Classifier: Programming Language :: Python :: 3
Requires-Python: >=3.10.0
